{
  "id": "helianas-harvesting",
  "title": "Heliana's Harvesting",
  "description": "<p>Initial Testing Version of a Harvesting Module to aid with Heliana's Harvesting Rules.</p>",
  "version": "0.3.1",
  "compatibility": {
    "minimum": "10",
    "verified": "11.315",
    "maximum": "11"
  },
  "authors": [
    {
      "name": "Kage",
      "discord": "Kage#6375"
    }
  ],
  "relationships": {
    "systems": [
      {
        "id": "dnd5e",
        "type": "system",
        "compatibility": {
          "minimum": "2.0.0",
          "verified": "3.0.1"
        }
      }
    ],
    "requires": []
  },
  "languages": [
    {
      "lang": "en",
      "name": "English",
      "path": "lang/en.json",
      "flags": {}
    }
  ],
  "packs": [
    {
      "name": "dnd5e-journals",
      "label": "Heliana's Harvesting Journals",
      "path": "packs/dnd5e-journals.db",
      "type": "JournalEntry",
      "system": "dnd5e"
    },
    {
      "name": "dnd5e-components",
      "label": "Heliana's Harvesting Components",
      "path": "packs/dnd5e-components.db",
      "type": "Item",
      "system": "dnd5e"
    }
  ],
  "styles": [
    "styles/style.css"
  ],
  "includes": [
    "data/harvesting-components.json",
    "lang/*",
    "packs/dnd5e-components.db",
    "packs/dnd5e-journals.db",
    "scripts/main.js",
    "styles/style.css",
    "templates/*",
    "LICENSE",
    "module.json",
    "OGL.md"
  ],
  "esmodules": [
    "./scripts/main.js"
  ],
  "url": "https://github.com/KageJittai/helianas-harvesting",
  "manifest": "https://github.com/KageJittai/helianas-harvesting/releases/latest/download/module.json",
  "download": "https://github.com/KageJittai/helianas-harvesting/releases/latest/download/module.zip"
}
